idservice/__init__.py
idservice/__main__.py
idservice/api.py
idservice/config.py
idservice/service.py
idservice-1.2.3.dist-info/entry_points.txt
idservice-1.2.3.dist-info/LICENSE
idservice-1.2.3.dist-info/WHEEL
idservice-1.2.3.dist-info/METADATA
idservice-1.2.3.dist-info/RECORD
